bytestkit/__init__.py
bytestkit/__version__.py
bytestkit/_internal_utils.py
bytestkit/db_manager.py
bytestkit/enums.py
bytestkit/exceptions.py
bytestkit/http_manager.py
bytestkit/logger.py
bytestkit/nacos_manager.py
bytestkit/redis_manager.py
bytestkit/utils.py
bytestkit-0.0.6.dist-info/LICENSE
bytestkit-0.0.6.dist-info/METADATA
bytestkit-0.0.6.dist-info/WHEEL
bytestkit-0.0.6.dist-info/top_level.txt
bytestkit-0.0.6.dist-info/RECORD
