Metadata-Version: 2.2
Name: bytestkit
Version: 0.0.6
Summary: Testkit is the spellbook. 🪄
Home-page: 
Author: /* This code is poetry */
License: Apache-2.0
Classifier: License :: OSI Approved :: Apache Software License
Classifier: Development Status :: 5 - Production/Stable
Classifier: Natural Language :: English
Classifier: Operating System :: OS Independent
Classifier: Programming Language :: Python :: 3.10
Classifier: Programming Language :: Python :: 3.11
Classifier: Programming Language :: Python :: 3.2
Classifier: Programming Language :: Python :: Implementation :: CPython
Classifier: Programming Language :: Python :: Implementation :: PyPy
Classifier: Topic :: Internet :: WWW/HTTP
Classifier: Topic :: Software Development :: Libraries
Requires-Python: >=3.8
License-File: LICENSE
Requires-Dist: tinydb
Requires-Dist: requests
Requires-Dist: redis
Requires-Dist: colorlog
Requires-Dist: pymysql
Requires-Dist: dbutils
Requires-Dist: nacos-sdk-python
Requires-Dist: pycryptodome
Dynamic: author
Dynamic: classifier
Dynamic: description
Dynamic: description-content-type
Dynamic: license
Dynamic: requires-dist
Dynamic: requires-python
Dynamic: summary
